overloadable/__init__.py
overloadable/core.py
overloadable/tests/__init__.py
overloadable/tests/test_classmethod.py
overloadable/tests/test_example_2.py
overloadable/tests/test_func.py
overloadable/tests/test_legacy.py
overloadable/tests/test_method.py
overloadable/tests/test_staticmethod.py
overloadable-1.0.14.dist-info/licenses/LICENSE.txt
overloadable-1.0.14.dist-info/METADATA
overloadable-1.0.14.dist-info/WHEEL
overloadable-1.0.14.dist-info/top_level.txt
overloadable-1.0.14.dist-info/RECORD
