Metadata-Version: 2.4
Name: overloadable
Version: 1.0.14
Summary: This projects allows overloading.
Author-email: Johannes <johannes.programming@gmail.com>
License: The MIT License (MIT)
Project-URL: Download, https://pypi.org/project/overloadable/#files
Project-URL: Index, https://pypi.org/project/overloadable/
Project-URL: Source, https://github.com/johannes-programming/overloadable/
Project-URL: Website, https://overloadable.johannes-programming.online/
Classifier: Development Status :: 5 - Production/Stable
Classifier: Intended Audience :: Developers
Classifier: License :: OSI Approved :: MIT License
Classifier: Natural Language :: English
Classifier: Operating System :: OS Independent
Classifier: Programming Language :: Python
Classifier: Programming Language :: Python :: 3
Classifier: Programming Language :: Python :: 3 :: Only
Classifier: Typing :: Typed
Requires-Python: >=3.11
License-File: LICENSE.txt
Requires-Dist: datarepr<2,>=1.0.2
Dynamic: license-file
